LICENSE
README.md
package_info.json
setup.py
tennis_new_library/__init__.py
tennis_new_library/py.typed
tennis_new_library/tennis_new.proto
tennis_new_library/tennis_new_pb2.py
tennis_new_library/tennis_new_pb2.pyi
tennis_new_library/tennis_new_pb2_grpc.py
tennis_new_library.egg-info/PKG-INFO
tennis_new_library.egg-info/SOURCES.txt
tennis_new_library.egg-info/dependency_links.txt
tennis_new_library.egg-info/requires.txt
tennis_new_library.egg-info/top_level.txt