Metadata-Version: 2.1
Name: tennis-new-library
Version: 1.0.0
Summary: tennis_new_library
Home-page: https://github.com/onskydeep/my_generator_test
Author: Alexander Oniani
Author-email: sandro.oniani@exactprosystems.com
License: Apache License 2.0
Platform: UNKNOWN
Requires-Python: >=3.7
License-File: LICENSE
